{"/about-me.html":"https://atharvacoolkarni.github.io/about-me/","/about/":"https://atharvacoolkarni.github.io/","/about.html":"https://atharvacoolkarni.github.io/","/wordpress/blog-posts/":"https://atharvacoolkarni.github.io/year-archive/","/resume-json":"https://atharvacoolkarni.github.io/cv-json/","/resume":"https://atharvacoolkarni.github.io/cv/","/interests.html":"https://atharvacoolkarni.github.io/interests/","/md/":"https://atharvacoolkarni.github.io/markdown/","/markdown.html":"https://atharvacoolkarni.github.io/markdown/","/nmp/":"https://atharvacoolkarni.github.io/non-menu-page/","/nmp.html":"https://atharvacoolkarni.github.io/non-menu-page/"}